plain_abc.py
plain_abc-0.1.0.dist-info/LICENSE
plain_abc-0.1.0.dist-info/METADATA
plain_abc-0.1.0.dist-info/WHEEL
plain_abc-0.1.0.dist-info/top_level.txt
plain_abc-0.1.0.dist-info/RECORD
