Metadata-Version: 2.1
Name: plain-abc
Version: 0.1.0
Summary: An ABC implementation without metaclass
Author-email: Chielo Newctle <ChieloNewctle@gmail.com>
License: MIT License
Project-URL: Homepage, https://github.com/ChieloNewctle/plain-abc
Project-URL: Bug Tracker, https://github.com/ChieloNewctle/plain-abc/issues
Classifier: Programming Language :: Python :: 3
Classifier: License :: OSI Approved :: MIT License
Classifier: Operating System :: OS Independent
Requires-Python: >=3.8
License-File: LICENSE
Provides-Extra: tests
Requires-Dist: pytest ; extra == 'tests'
